echolib/__init__.py
echolib/common/__init__.py
echolib/common/config_manager.py
echolib/common/logger.py
echolib/common/models.py
echolib/models/__init__.py
echolib/models/base.py
echolib/models/hf.py
echolib/models/lm_studio.py
echolib/models/model_manager.py
tests/__init__.py
tests/test_common.py
tests/test_models.py
tests/test_utils.py
echolib-0.2.0.dist-info/LICENSE
echolib-0.2.0.dist-info/METADATA
echolib-0.2.0.dist-info/WHEEL
echolib-0.2.0.dist-info/top_level.txt
echolib-0.2.0.dist-info/RECORD
