Metadata-Version: 2.1
Name: echolib
Version: 0.2.0
Summary: An AI-driven library for generating content using HuggingFace and LMStudio models.
Home-page: https://github.com/ayoubachak/echolib
Author: Ayoub Achak
Author-email: ayoub.achak01@example.com
Classifier: Programming Language :: Python :: 3
Classifier: License :: OSI Approved :: MIT License
Classifier: Operating System :: OS Independent
Requires-Python: >=3.8
License-File: LICENSE
Requires-Dist: requests
Requires-Dist: transformers
Requires-Dist: colorlog
Requires-Dist: pyfiglet
Requires-Dist: termcolor
Requires-Dist: openai
Requires-Dist: appdirs
